[
  {
    "token": "付费类型",
    "user_info": {
      "是否会员": [
        "是",
        "否"
      ],
      "消费偏好": [
        "付费",
        "不付费"
      ]
    },
    "information": {
      "是否会员": "会员可以观看会员片",
      "消费偏好": "偏好不付费的观众一般只会看免费片，"
    }
  },
  {
    "token": "类型",
    "user_info": {
      "最常观看类型": "None"

    },
    "information": {
      "最常观看类型": "None"
    }
  },
  {
    "token": "地区",
    "user_info": {
      "最多观看语种": ["普通话","英语","粤语","印度语","韩语","日语","泰语"]

    },
    "information": {
      "最多观看语种": "可以通过该地区人民说的话推测出语种"
    }
  }
]