[
  {
    "token": "变速箱",
    "user_info": {
      "驾照类型": [
        "C1",
        "C2"
      ]
    },
    "information": {
      "驾照类型": "C1型驾照可以开手动或自动挡车，C2型驾照只能开自动挡车"
    }
  },
   {
    "token": "价格",
    "user_info": {
       "年薪": [
        "2万以下",
        "2-5万",
        "5-10万",
        "10-25万",
        "25-50万",
        "50-100万",
        "100万以上"
      ]
    },
    "information": {
      "年薪": "购买车辆时，车的价格应为年薪的20%-30%"
    }
  },
  {
    "token": "座位数",
    "user_info": {
      "家庭人口": ["1人","2人","3人","4人","5人","6人"]
    },
    "information": {
      "家庭人口": "座位数应该多于或等于家庭人口"
    }
  }
]